{
    "timestamp": "2024-11-27T20:11:48.317535",
    "game_info": {
        "id": 14390,
        "home_team": {
            "id": "28",
            "name": "Phoenix Suns",
            "code": ""
        },
        "away_team": {
            "id": "4",
            "name": "Brooklyn Nets",
            "code": ""
        },
        "scheduled_start": "2024-11-28T02:00:00.000Z",
        "period": 0,
        "clock": "12:00",
        "score": {
            "home": 0,
            "away": 0
        }
    },
    "prediction": {
        "base": 0.5678868157026317,
        "adjusted": 0.5678868157026317,
        "predicted_winner": "Phoenix Suns",
        "win_probability": 0.5678868157026317,
        "confidence_level": "Low",
        "model_predictions": {
            "random_forest": 0.5286847866421137,
            "xgboost": 0.5447333455085754,
            "svm": 0.5929227762306781,
            "lstm": 0.7592061758041382,
            "gru": 0.43325453996658325
        },
        "score_prediction": {
            "home_low": 101,
            "home_high": 123,
            "away_low": 100,
            "away_high": 122
        }
    }
}